flask_swagger_ui/LICENSE
flask_swagger_ui/README.md
flask_swagger_ui/__init__.py
flask_swagger_ui/flask_swagger_ui.py
flask_swagger_ui/dist/LICENSE
flask_swagger_ui/dist/VERSION
flask_swagger_ui/dist/favicon-16x16.png
flask_swagger_ui/dist/favicon-32x32.png
flask_swagger_ui/dist/index.css
flask_swagger_ui/dist/oauth2-redirect.html
flask_swagger_ui/dist/swagger-ui-bundle.js
flask_swagger_ui/dist/swagger-ui-bundle.js.map
flask_swagger_ui/dist/swagger-ui-standalone-preset.js
flask_swagger_ui/dist/swagger-ui-standalone-preset.js.map
flask_swagger_ui/dist/swagger-ui.css
flask_swagger_ui/dist/swagger-ui.css.map
flask_swagger_ui/dist/swagger-ui.js
flask_swagger_ui/dist/swagger-ui.js.map
flask_swagger_ui/templates/index.template.html
flask_swagger_ui-4.11.1.dist-info/LICENSE
flask_swagger_ui-4.11.1.dist-info/METADATA
flask_swagger_ui-4.11.1.dist-info/WHEEL
flask_swagger_ui-4.11.1.dist-info/top_level.txt
flask_swagger_ui-4.11.1.dist-info/RECORD
