Metadata-Version: 2.1
Name: flask-swagger-ui
Version: 4.11.1
Summary: Swagger UI blueprint for Flask
Home-page: https://github.com/sveint/flask-swagger-ui
Author: Svein Tore Koksrud Seljebotn
Author-email: sveint@gmail.com
License: MIT
Keywords: flask swagger
Classifier: Development Status :: 4 - Beta
Classifier: Intended Audience :: Developers
Classifier: License :: OSI Approved :: MIT License
Classifier: Programming Language :: Python :: 2
Classifier: Programming Language :: Python :: 2.6
Classifier: Programming Language :: Python :: 2.7
Classifier: Programming Language :: Python :: 3
Classifier: Programming Language :: Python :: 3.6
License-File: LICENSE
